Topsis_Pramit_101903198/__init__.py
Topsis_Pramit_101903198/topsis_Pramit.py
Topsis_Pramit_101903198-1.0.2.dist-info/LICENSE
Topsis_Pramit_101903198-1.0.2.dist-info/METADATA
Topsis_Pramit_101903198-1.0.2.dist-info/WHEEL
Topsis_Pramit_101903198-1.0.2.dist-info/entry_points.txt
Topsis_Pramit_101903198-1.0.2.dist-info/top_level.txt
Topsis_Pramit_101903198-1.0.2.dist-info/RECORD
