Metadata-Version: 2.1
Name: Topsis-Pramit-101903198
Version: 1.0.2
Summary: Multi-Criteria Decision Making
Home-page: https://github.com/Pramit29/Topsis-Pramit-101903198
Author: Pramit
License: MIT
Keywords: python,best model,Topsis,multi-criteria decision making,assignment
Classifier: Programming Language :: Python :: 3
Classifier: License :: OSI Approved :: MIT License
Classifier: Operating System :: OS Independent
License-File: LICENSE
Requires-Dist: pandas
